Metadata-Version: 2.1
Name: Nipo
Version: 0.0.1
Summary: Awesome Wsgi Framework
Home-page: https://github.com/harsha7addanki/Nipo
Author: Harsha Addanki
Author-email: harsha7addanki@gmail.com
License: UNKNOWN
Platform: UNKNOWN
Classifier: Programming Language :: Python :: 3
Classifier: License :: OSI Approved :: MIT License
Classifier: Operating System :: OS Independent
Requires-Python: >=3.8
